{"FC01_Session1_0014": {"have_silence": true, "time": [1.024, 1.548]}, "FC01_Session1_0130": {"have_silence": true, "time": [0, 2.572]}, "FC01_Session1_0227": {"have_silence": true, "time": [0.896, 1.164]}, "FC01_Session1_0068": {"have_silence": true, "time": [1.024, 1.676]}, "FC01_Session1_0137": {"have_silence": true, "time": [0.896, 1.292]}, "FC01_Session1_0220": {"have_silence": true, "time": [0.512, 0.908]}, "FC01_Session1_0013": {"have_silence": true, "time": [1.152, 1.548]}, "FC01_Session1_0139": {"have_silence": true, "time": [0.512, 2.956]}, "FC01_Session1_0061": {"have_silence": true, "time": [1.152, 5.388]}, "FC01_Session1_0145": {"have_silence": true, "time": [0.896, 1.292]}, "FC01_Session1_0194": {"have_silence": true, "time": [0, 2.7]}, "FC01_Session1_0252": {"have_silence": true, "time": [0.64, 1.036]}, "FC01_Session1_0142": {"have_silence": false, "time": [0, 0]}, "FC01_Session1_0193": {"have_silence": true, "time": [0.768, 1.292]}, "FC01_Session1_0255": {"have_silence": true, "time": [0.768, 1.036]}, "FC01_Session1_0229": {"have_silence": false, "time": [0, 0]}, "FC01_Session1_0066": {"have_silence": true, "time": [1.024, 1.676]}, "FC01_Session1_0177": {"have_silence": true, "time": [0, 2.572]}, "FC01_Session1_0053": {"have_silence": true, "time": [0.768, 1.292]}, "FC01_Session1_0082": {"have_silence": true, "time": [0.768, 1.164]}, "FC01_Session1_0054": {"have_silence": true, "time": [1.024, 3.596]}, "FC01_Session1_0085": {"have_silence": true, "time": [0.768, 2.7]}, "FC01_Session1_0170": {"have_silence": true, "time": [0.64, 1.292]}, "FC01_Session1_0028": {"have_silence": true, "time": [0.768, 1.292]}, "FC01_Session1_0215": {"have_silence": true, "time": [0.896, 1.42]}, "FC01_Session1_0102": {"have_silence": true, "time": [0.896, 4.364]}, "FC01_Session1_0026": {"have_silence": true, "time": [0.768, 4.62]}, "FC01_Session1_0179": {"have_silence": true, "time": [0.896, 2.7]}, "FC01_Session1_0021": {"have_silence": true, "time": [0.896, 1.42]}, "FC01_Session1_0212": {"have_silence": true, "time": [1.024, 1.292]}, "FC01_Session1_0105": {"have_silence": true, "time": [0, 0.396]}, "FC01_Session1_0030": {"have_silence": true, "time": [1.024, 1.292]}, "FC01_Session1_0168": {"have_silence": true, "time": [0.768, 1.292]}, "FC01_Session1_0114": {"have_silence": true, "time": [0.896, 3.468]}, "FC01_Session1_0203": {"have_silence": true, "time": [0.768, 1.036]}, "FC01_Session1_0113": {"have_silence": true, "time": [1.024, 3.98]}, "FC01_Session1_0204": {"have_silence": true, "time": [0.512, 2.444]}, "FC01_Session1_0037": {"have_silence": true, "time": [0.768, 1.164]}, "FC01_Session1_0094": {"have_silence": true, "time": [0.896, 1.42]}, "FC01_Session1_0045": {"have_silence": true, "time": [0.768, 1.42]}, "FC01_Session1_0039": {"have_silence": true, "time": [0.768, 1.164]}, "FC01_Session1_0161": {"have_silence": true, "time": [1.024, 3.852]}, "FC01_Session1_0166": {"have_silence": true, "time": [0.768, 1.548]}, "FC01_Session1_0093": {"have_silence": true, "time": [0.768, 1.164]}, "FC01_Session1_0042": {"have_silence": true, "time": [1.152, 3.75]}, "FC01_Session1_0182": {"have_silence": true, "time": [0.768, 1.164]}, "FC01_Session1_0244": {"have_silence": true, "time": [0.768, 1.292]}, "FC01_Session1_0153": {"have_silence": true, "time": [0.896, 1.42]}, "FC01_Session1_0077": {"have_silence": true, "time": [0, 2.316]}, "FC01_Session1_0238": {"have_silence": true, "time": [0.768, 1.164]}, "FC01_Session1_0070": {"have_silence": true, "time": [1.024, 1.292]}, "FC01_Session1_0128": {"have_silence": true, "time": [0.896, 2.06]}, "FC01_Session1_0185": {"have_silence": true, "time": [0.896, 1.292]}, "FC01_Session1_0243": {"have_silence": true, "time": [0.768, 1.036]}, "FC01_Session1_0154": {"have_silence": true, "time": [0.896, 1.42]}, "FC01_Session1_0231": {"have_silence": true, "time": [0.768, 1.42]}, "FC01_Session1_0126": {"have_silence": true, "time": [0.896, 1.42]}, "FC01_Session1_0002": {"have_silence": true, "time": [1.024, 7.35]}, "FC01_Session1_0005": {"have_silence": true, "time": [0.768, 1.164]}, "FC01_Session1_0079": {"have_silence": true, "time": [0.896, 1.292]}, "FC01_Session1_0236": {"have_silence": true, "time": [0.768, 1.164]}, "FC01_Session1_0121": {"have_silence": true, "time": [0.896, 1.42]}, "FC01_Session1_0178": {"have_silence": true, "time": [0, 1.42]}, "FC01_Session1_0020": {"have_silence": true, "time": [0.896, 1.292]}, "FC01_Session1_0213": {"have_silence": true, "time": [0.896, 1.292]}, "FC01_Session1_0104": {"have_silence": true, "time": [0.512, 6.15]}, "FC01_Session1_0214": {"have_silence": true, "time": [0.768, 1.036]}, "FC01_Session1_0103": {"have_silence": true, "time": [1.024, 5.85]}, "FC01_Session1_0027": {"have_silence": false, "time": [0, 0]}, "FC01_Session1_0055": {"have_silence": true, "time": [1.024, 1.42]}, "FC01_Session1_0084": {"have_silence": true, "time": [0.896, 3.468]}, "FC01_Session1_0171": {"have_silence": true, "time": [0.896, 1.42]}, "FC01_Session1_0029": {"have_silence": true, "time": [0.768, 1.164]}, "FC01_Session1_0176": {"have_silence": false, "time": [0, 0]}, "FC01_Session1_0052": {"have_silence": true, "time": [0.64, 1.42]}, "FC01_Session1_0083": {"have_silence": true, "time": [0.768, 1.164]}, "FC01_Session1_0143": {"have_silence": true, "time": [0.768, 1.292]}, "FC01_Session1_0192": {"have_silence": true, "time": [0.896, 3.212]}, "FC01_Session1_0254": {"have_silence": true, "time": [0.64, 1.164]}, "FC01_Session1_0228": {"have_silence": true, "time": [0.64, 3.15]}, "FC01_Session1_0067": {"have_silence": true, "time": [1.024, 1.42]}, "FC01_Session1_0138": {"have_silence": true, "time": [0.896, 1.42]}, "FC01_Session1_0060": {"have_silence": true, "time": [0.896, 1.164]}, "FC01_Session1_0144": {"have_silence": true, "time": [0.768, 1.292]}, "FC01_Session1_0195": {"have_silence": true, "time": [0.768, 1.292]}, "FC01_Session1_0253": {"have_silence": true, "time": [0.768, 3.084]}, "FC01_Session1_0136": {"have_silence": true, "time": [0.768, 1.292]}, "FC01_Session1_0221": {"have_silence": true, "time": [0.768, 2.316]}, "FC01_Session1_0012": {"have_silence": true, "time": [0.768, 1.292]}, "FC01_Session1_0015": {"have_silence": true, "time": [0, 4.236]}, "FC01_Session1_0131": {"have_silence": true, "time": [0.896, 1.42]}, "FC01_Session1_0226": {"have_silence": true, "time": [0.896, 1.292]}, "FC01_Session1_0069": {"have_silence": true, "time": [0.896, 1.292]}, "FC01_Session1_0004": {"have_silence": false, "time": [0, 0]}, "FC01_Session1_0078": {"have_silence": true, "time": [0.768, 1.42]}, "FC01_Session1_0237": {"have_silence": true, "time": [0.896, 1.292]}, "FC01_Session1_0120": {"have_silence": true, "time": [0.896, 1.42]}, "FC01_Session1_0230": {"have_silence": true, "time": [0, 1.164]}, "FC01_Session1_0127": {"have_silence": false, "time": [0, 0]}, "FC01_Session1_0003": {"have_silence": true, "time": [0, 0.396]}, "FC01_Session1_0071": {"have_silence": true, "time": [1.024, 1.548]}, "FC01_Session1_0129": {"have_silence": true, "time": [1.28, 1.676]}, "FC01_Session1_0184": {"have_silence": true, "time": [1.024, 1.548]}, "FC01_Session1_0242": {"have_silence": true, "time": [0.64, 2.188]}, "FC01_Session1_0155": {"have_silence": true, "time": [0, 1.932]}, "FC01_Session1_0183": {"have_silence": true, "time": [0.768, 1.548]}, "FC01_Session1_0245": {"have_silence": true, "time": [0.768, 1.164]}, "FC01_Session1_0152": {"have_silence": true, "time": [0.768, 1.292]}, "FC01_Session1_0076": {"have_silence": true, "time": [2.56, 4.95]}, "FC01_Session1_0239": {"have_silence": true, "time": [0.768, 3.084]}, "FC01_Session1_0167": {"have_silence": true, "time": [0.64, 1.036]}, "FC01_Session1_0092": {"have_silence": true, "time": [0.896, 1.548]}, "FC01_Session1_0043": {"have_silence": true, "time": [1.792, 1.804]}, "FC01_Session1_0095": {"have_silence": true, "time": [1.024, 1.42]}, "FC01_Session1_0044": {"have_silence": true, "time": [1.024, 1.676]}, "FC01_Session1_0038": {"have_silence": true, "time": [0.896, 1.164]}, "FC01_Session1_0160": {"have_silence": true, "time": [0.896, 1.036]}, "FC01_Session1_0112": {"have_silence": true, "time": [0.768, 1.164]}, "FC01_Session1_0205": {"have_silence": true, "time": [0.768, 1.292]}, "FC01_Session1_0036": {"have_silence": true, "time": [0.896, 4.108]}, "FC01_Session1_0031": {"have_silence": true, "time": [1.152, 1.676]}, "FC01_Session1_0169": {"have_silence": true, "time": [0.896, 1.292]}, "FC01_Session1_0115": {"have_silence": true, "time": [0.896, 1.42]}, "FC01_Session1_0202": {"have_silence": true, "time": [0, 0]}, "FC01_Session1_0233": {"have_silence": true, "time": [0.768, 5.004]}, "FC01_Session1_0124": {"have_silence": true, "time": [0.768, 1.164]}, "FC01_Session1_0189": {"have_silence": true, "time": [0.896, 1.292]}, "FC01_Session1_0158": {"have_silence": true, "time": [0.64, 1.292]}, "FC01_Session1_0007": {"have_silence": true, "time": [0, 0.652]}, "FC01_Session1_0248": {"have_silence": true, "time": [0.768, 1.164]}, "FC01_Session1_0234": {"have_silence": true, "time": [0.768, 1.42]}, "FC01_Session1_0123": {"have_silence": true, "time": [0.896, 7.5]}, "FC01_Session1_0009": {"have_silence": true, "time": [0, 1.036]}, "FC01_Session1_0246": {"have_silence": true, "time": [0.896, 1.292]}, "FC01_Session1_0180": {"have_silence": true, "time": [0.896, 1.292]}, "FC01_Session1_0151": {"have_silence": true, "time": [0, 0.652]}, "FC01_Session1_0075": {"have_silence": true, "time": [1.152, 5.4]}, "FC01_Session1_0072": {"have_silence": true, "time": [1.28, 5.004]}, "FC01_Session1_0241": {"have_silence": true, "time": [0.768, 1.036]}, "FC01_Session1_0187": {"have_silence": true, "time": [0, 0.78]}, "FC01_Session1_0156": {"have_silence": true, "time": [0.896, 1.164]}, "FC01_Session1_0096": {"have_silence": true, "time": [0.896, 1.42]}, "FC01_Session1_0047": {"have_silence": true, "time": [0.768, 3.468]}, "FC01_Session1_0208": {"have_silence": true, "time": [0.896, 1.292]}, "FC01_Session1_0163": {"have_silence": true, "time": [0.896, 1.42]}, "FC01_Session1_0164": {"have_silence": true, "time": [0.768, 2.4]}, "FC01_Session1_0091": {"have_silence": true, "time": [0, 1.42]}, "FC01_Session1_0040": {"have_silence": true, "time": [1.536, 3.852]}, "FC01_Session1_0118": {"have_silence": true, "time": [1.024, 1.548]}, "FC01_Session1_0032": {"have_silence": true, "time": [1.024, 1.676]}, "FC01_Session1_0116": {"have_silence": true, "time": [1.152, 1.676]}, "FC01_Session1_0201": {"have_silence": true, "time": [0.768, 2.828]}, "FC01_Session1_0098": {"have_silence": true, "time": [1.024, 1.548]}, "FC01_Session1_0049": {"have_silence": true, "time": [1.024, 1.548]}, "FC01_Session1_0111": {"have_silence": true, "time": [0.768, 3.212]}, "FC01_Session1_0206": {"have_silence": true, "time": [0.896, 9.15]}, "FC01_Session1_0035": {"have_silence": true, "time": [0.896, 1.292]}, "FC01_Session1_0217": {"have_silence": true, "time": [0.64, 1.292]}, "FC01_Session1_0100": {"have_silence": true, "time": [1.024, 1.42]}, "FC01_Session1_0058": {"have_silence": true, "time": [1.024, 1.548]}, "FC01_Session1_0089": {"have_silence": true, "time": [0.896, 1.164]}, "FC01_Session1_0024": {"have_silence": true, "time": [0.896, 1.42]}, "FC01_Session1_0023": {"have_silence": true, "time": [0, 11.02]}, "FC01_Session1_0210": {"have_silence": true, "time": [0.64, 1.036]}, "FC01_Session1_0107": {"have_silence": true, "time": [0.896, 1.548]}, "FC01_Session1_0175": {"have_silence": true, "time": [0, 0.652]}, "FC01_Session1_0109": {"have_silence": true, "time": [0.896, 1.292]}, "FC01_Session1_0051": {"have_silence": true, "time": [2.688, 3.0]}, "FC01_Session1_0080": {"have_silence": true, "time": [1.024, 9.228]}, "FC01_Session1_0219": {"have_silence": true, "time": [0.768, 1.292]}, "FC01_Session1_0056": {"have_silence": true, "time": [0.896, 1.548]}, "FC01_Session1_0087": {"have_silence": true, "time": [0.768, 1.292]}, "FC01_Session1_0172": {"have_silence": true, "time": [0.896, 1.548]}, "FC01_Session1_0063": {"have_silence": true, "time": [0.896, 1.42]}, "FC01_Session1_0147": {"have_silence": true, "time": [1.024, 1.548]}, "FC01_Session1_0250": {"have_silence": true, "time": [1.024, 3.0]}, "FC01_Session1_0196": {"have_silence": true, "time": [0.768, 2.956]}, "FC01_Session1_0140": {"have_silence": true, "time": [0.896, 2.7]}, "FC01_Session1_0191": {"have_silence": true, "time": [0.768, 2.956]}, "FC01_Session1_0018": {"have_silence": true, "time": [0.896, 1.42]}, "FC01_Session1_0064": {"have_silence": false, "time": [0, 0]}, "FC01_Session1_0016": {"have_silence": true, "time": [0.768, 1.164]}, "FC01_Session1_0132": {"have_silence": true, "time": [0.896, 1.42]}, "FC01_Session1_0225": {"have_silence": true, "time": [0.768, 1.164]}, "FC01_Session1_0135": {"have_silence": true, "time": [0.896, 1.548]}, "FC01_Session1_0222": {"have_silence": true, "time": [0.768, 2.956]}, "FC01_Session1_0149": {"have_silence": true, "time": [1.024, 1.548]}, "FC01_Session1_0198": {"have_silence": true, "time": [0.768, 1.292]}, "FC01_Session1_0011": {"have_silence": true, "time": [0.896, 1.42]}, "FC01_Session1_0099": {"have_silence": true, "time": [1.152, 1.676]}, "FC01_Session1_0048": {"have_silence": true, "time": [1.152, 1.42]}, "FC01_Session1_0110": {"have_silence": true, "time": [1.024, 1.548]}, "FC01_Session1_0207": {"have_silence": true, "time": [1.024, 2.7]}, "FC01_Session1_0034": {"have_silence": true, "time": [0.896, 1.164]}, "FC01_Session1_0033": {"have_silence": true, "time": [0.768, 5.004]}, "FC01_Session1_0117": {"have_silence": true, "time": [1.28, 1.676]}, "FC01_Session1_0200": {"have_silence": true, "time": [0.896, 2.828]}, "FC01_Session1_0165": {"have_silence": true, "time": [0, 0.78]}, "FC01_Session1_0090": {"have_silence": true, "time": [0.896, 6.412]}, "FC01_Session1_0041": {"have_silence": true, "time": [0.896, 1.292]}, "FC01_Session1_0119": {"have_silence": true, "time": [0.896, 1.548]}, "FC01_Session1_0097": {"have_silence": true, "time": [1.024, 1.548]}, "FC01_Session1_0046": {"have_silence": true, "time": [0.896, 4.364]}, "FC01_Session1_0209": {"have_silence": true, "time": [0.768, 2.956]}, "FC01_Session1_0162": {"have_silence": true, "time": [0, 0.78]}, "FC01_Session1_0073": {"have_silence": true, "time": [1.024, 1.548]}, "FC01_Session1_0240": {"have_silence": true, "time": [0.512, 1.036]}, "FC01_Session1_0186": {"have_silence": true, "time": [0.896, 3.596]}, "FC01_Session1_0157": {"have_silence": true, "time": [0.768, 2.188]}, "FC01_Session1_0008": {"have_silence": true, "time": [1.024, 1.42]}, "FC01_Session1_0247": {"have_silence": true, "time": [0.768, 2.572]}, "FC01_Session1_0181": {"have_silence": true, "time": [0.896, 2.956]}, "FC01_Session1_0150": {"have_silence": true, "time": [0.896, 2.572]}, "FC01_Session1_0074": {"have_silence": true, "time": [1.28, 1.676]}, "FC01_Session1_0006": {"have_silence": true, "time": [0.896, 1.292]}, "FC01_Session1_0249": {"have_silence": true, "time": [0, 1.804]}, "FC01_Session1_0235": {"have_silence": true, "time": [0.768, 1.292]}, "FC01_Session1_0122": {"have_silence": true, "time": [0.896, 1.292]}, "FC01_Session1_0232": {"have_silence": true, "time": [0.768, 1.292]}, "FC01_Session1_0125": {"have_silence": true, "time": [0.896, 1.42]}, "FC01_Session1_0001": {"have_silence": true, "time": [1.28, 9.3]}, "FC01_Session1_0188": {"have_silence": true, "time": [0.768, 2.444]}, "FC01_Session1_0159": {"have_silence": true, "time": [0.768, 1.292]}, "FC01_Session1_0134": {"have_silence": true, "time": [1.152, 1.676]}, "FC01_Session1_0223": {"have_silence": true, "time": [0.896, 1.292]}, "FC01_Session1_0148": {"have_silence": true, "time": [0.896, 1.42]}, "FC01_Session1_0199": {"have_silence": true, "time": [0.64, 2.7]}, "FC01_Session1_0010": {"have_silence": true, "time": [0.64, 1.164]}, "FC01_Session1_0017": {"have_silence": true, "time": [0.896, 1.42]}, "FC01_Session1_0133": {"have_silence": true, "time": [1.024, 2.956]}, "FC01_Session1_0224": {"have_silence": true, "time": [0.64, 1.036]}, "FC01_Session1_0141": {"have_silence": true, "time": [0.64, 1.164]}, "FC01_Session1_0190": {"have_silence": true, "time": [0.896, 3.212]}, "FC01_Session1_0019": {"have_silence": true, "time": [1.024, 1.676]}, "FC01_Session1_0065": {"have_silence": true, "time": [0.896, 1.42]}, "FC01_Session1_0062": {"have_silence": true, "time": [0.896, 1.292]}, "FC01_Session1_0146": {"have_silence": true, "time": [0.64, 1.164]}, "FC01_Session1_0251": {"have_silence": true, "time": [0.768, 1.292]}, "FC01_Session1_0197": {"have_silence": true, "time": [0.64, 2.188]}, "FC01_Session1_0218": {"have_silence": true, "time": [0.768, 1.164]}, "FC01_Session1_0057": {"have_silence": true, "time": [1.28, 1.676]}, "FC01_Session1_0086": {"have_silence": true, "time": [1.024, 1.42]}, "FC01_Session1_0173": {"have_silence": true, "time": [0.896, 1.548]}, "FC01_Session1_0174": {"have_silence": true, "time": [1.024, 3.596]}, "FC01_Session1_0108": {"have_silence": true, "time": [0.896, 1.42]}, "FC01_Session1_0050": {"have_silence": true, "time": [1.152, 1.804]}, "FC01_Session1_0081": {"have_silence": true, "time": [0.768, 1.164]}, "FC01_Session1_0022": {"have_silence": true, "time": [0.896, 1.42]}, "FC01_Session1_0211": {"have_silence": true, "time": [0, 2.316]}, "FC01_Session1_0106": {"have_silence": true, "time": [0, 1.164]}, "FC01_Session1_0216": {"have_silence": true, "time": [0, 0.652]}, "FC01_Session1_0101": {"have_silence": true, "time": [0, 0.78]}, "FC01_Session1_0059": {"have_silence": true, "time": [0, 0]}, "FC01_Session1_0088": {"have_silence": true, "time": [0.768, 1.292]}, "FC01_Session1_0025": {"have_silence": true, "time": [0.896, 6.3]}}